pyz3/__init__.py
pyz3/__main__.py
pyz3/auto_stubs.py
pyz3/build.py
pyz3/buildzig.py
pyz3/config.py
pyz3/debug.py
pyz3/deploy.py
pyz3/deps.py
pyz3/develop.py
pyz3/generate_stubs.py
pyz3/init.py
pyz3/logging_config.py
pyz3/py.typed
pyz3/pyZ3-template/.cookiecutterrc
pyz3/pyZ3-template/.github/workflows/ci.yml
pyz3/pyZ3-template/.github/workflows/publish.yml
pyz3/pyZ3-template/.gitignore
pyz3/pyZ3-template/.vscode/extensions.json
pyz3/pyZ3-template/.vscode/launch.json
pyz3/pyZ3-template/CLEANUP_SUMMARY.md
pyz3/pyZ3-template/CONVERSION_SUMMARY.md
pyz3/pyZ3-template/LICENSE
pyz3/pyZ3-template/QUICKSTART.md
pyz3/pyZ3-template/README.md
pyz3/pyZ3-template/TEMPLATE_RENAME_SUMMARY.md
pyz3/pyZ3-template/TEMPLATE_STRUCTURE.md
pyz3/pyZ3-template/USAGE.md
pyz3/pyZ3-template/cookiecutter.json
pyz3/pyZ3-template/hooks/post_gen_project.py
pyz3/pyZ3-template/validate_template.py
pyz3/pyZ3-template/{{cookiecutter.project_slug}}/.github/workflows/ci.yml
pyz3/pyZ3-template/{{cookiecutter.project_slug}}/.github/workflows/publish.yml
pyz3/pyZ3-template/{{cookiecutter.project_slug}}/.gitignore
pyz3/pyZ3-template/{{cookiecutter.project_slug}}/.vscode/extensions.json
pyz3/pyZ3-template/{{cookiecutter.project_slug}}/.vscode/launch.json
pyz3/pyZ3-template/{{cookiecutter.project_slug}}/LICENSE
pyz3/pyZ3-template/{{cookiecutter.project_slug}}/README.md
pyz3/pyZ3-template/{{cookiecutter.project_slug}}/build.py
pyz3/pyZ3-template/{{cookiecutter.project_slug}}/include/{{cookiecutter.c_helper_name}}.h
pyz3/pyZ3-template/{{cookiecutter.project_slug}}/pyproject.toml
pyz3/pyZ3-template/{{cookiecutter.project_slug}}/renovate.json
pyz3/pyZ3-template/{{cookiecutter.project_slug}}/src/{{cookiecutter.c_helper_name}}.c
pyz3/pyZ3-template/{{cookiecutter.project_slug}}/src/{{cookiecutter.zig_file_name}}.zig
pyz3/pyZ3-template/{{cookiecutter.project_slug}}/test/__init__.py
pyz3/pyZ3-template/{{cookiecutter.project_slug}}/test/test_{{cookiecutter.zig_file_name}}.py
pyz3-0.9.0.dist-info/METADATA
pyz3-0.9.0.dist-info/WHEEL
pyz3-0.9.0.dist-info/entry_points.txt
pyz3-0.9.0.dist-info/licenses/LICENSE
pyz3-0.9.0.dist-info/RECORD
