Metadata-Version: 2.4
Name: pyz3
Version: 0.9.0
Summary: Build high-performance Python extensions in Zig with automatic memory management. Inspired by ziggy-pydust.
License: Apache 2.0
License-File: LICENSE
Keywords: zig,python,extensions,performance,c-api,bindings,pyz3
Author: amiya mandal
Author-email: amiya19mandal@pm.me
Requires-Python: >=3.11,<4.0
Classifier: Development Status :: 4 - Beta
Classifier: Intended Audience :: Developers
Classifier: License :: OSI Approved :: Apache Software License
Classifier: License :: Other/Proprietary License
Classifier: Operating System :: OS Independent
Classifier: Programming Language :: Other
Classifier: Programming Language :: Python :: 3
Classifier: Programming Language :: Python :: 3.11
Classifier: Programming Language :: Python :: 3.12
Classifier: Programming Language :: Python :: 3.13
Classifier: Programming Language :: Python :: 3.14
Classifier: Programming Language :: Python :: Implementation :: CPython
Classifier: Topic :: Software Development :: Build Tools
Classifier: Topic :: Software Development :: Code Generators
Classifier: Topic :: Software Development :: Compilers
Provides-Extra: dist
Requires-Dist: black (>=25.0.0,<26.0.0)
Requires-Dist: build (>=1.0.0,<2.0.0) ; extra == "dist"
Requires-Dist: cookiecutter (>=2.6.0,<3.0.0)
Requires-Dist: numpy (>=2.0.0,<3.0.0)
Requires-Dist: pydantic (>=2.3.0,<3.0.0)
Requires-Dist: pytest-asyncio (>=1.3.0,<2.0.0)
Requires-Dist: setuptools (>=80.0.0,<81.0.0)
Requires-Dist: twine (>=5.0.0,<6.0.0) ; extra == "dist"
Requires-Dist: wheel (>=0.43.0,<0.44.0) ; extra == "dist"
Requires-Dist: ziglang (>=0.15.1,<0.16.0)
Project-URL: Documentation, https://github.com/amiyamandal-dev/pyz3
Project-URL: Homepage, https://github.com/amiyamandal-dev/pyz3
Project-URL: Repository, https://github.com/amiyamandal-dev/pyz3
